overfast/__init__.py
overfast_py-1.2.dist-info/LICENSE
overfast_py-1.2.dist-info/METADATA
overfast_py-1.2.dist-info/WHEEL
overfast_py-1.2.dist-info/top_level.txt
overfast_py-1.2.dist-info/RECORD
