Metadata-Version: 2.1
Name: overfast-py
Version: 1.2
Summary: An API wrapper for the OverFast API
Author: amemoia
Classifier: Programming Language :: Python :: 3
Classifier: License :: OSI Approved :: MIT License
Classifier: Operating System :: OS Independent
Requires-Python: >=3.7
License-File: LICENSE
Requires-Dist: requests
